pycounts_sj/__init__.py
pycounts_sj/plotting.py
pycounts_sj/pycounts_sj.py
pycounts_sj-0.1.0.dist-info/LICENSE
pycounts_sj-0.1.0.dist-info/WHEEL
pycounts_sj-0.1.0.dist-info/METADATA
pycounts_sj-0.1.0.dist-info/RECORD
