Metadata-Version: 2.1
Name: pycounts-sj
Version: 0.1.0
Summary: A package for counting words
License: MIT
Author: Shiva Jena
Requires-Python: >=3.9,<4.0
Classifier: License :: OSI Approved :: MIT License
Classifier: Programming Language :: Python :: 3
Classifier: Programming Language :: Python :: 3.10
Classifier: Programming Language :: Python :: 3.9
Requires-Dist: matplotlib (>=3.5.1,<4.0.0)
